mdreader/__init__.py
mdreader/fmi.py
mdreader/fmi2.py
mdreader/fmi3.py
mdreader/py.typed
mdreader-0.3.1.dist-info/WHEEL
mdreader-0.3.1.dist-info/METADATA
mdreader-0.3.1.dist-info/RECORD
