Metadata-Version: 2.3
Name: mdreader
Version: 0.3.1
Summary: A Python library for reading and parsing Functional Mock-up Interface model description XML file.
Author: coder
Author-email: coder <coder@timeintegral.ai>
License: 
Requires-Dist: pydantic>=2.11.5,<3.0.0
Requires-Python: >=3.11
Project-URL: Repository, https://github.com/time-integral/mdreader
